LICENSE
pylineage/__init__.py
pylineage/graph.py
pylineage/helpers.py
pylineage/parser.py
pylineage/templates/index.html
pylineage-0.1.4.dist-info/LICENSE
pylineage-0.1.4.dist-info/WHEEL
pylineage-0.1.4.dist-info/METADATA
pylineage-0.1.4.dist-info/RECORD
